nonebot_plugin_trans_progress/__init__.py
nonebot_plugin_trans_progress/broadcast.py
nonebot_plugin_trans_progress/config.py
nonebot_plugin_trans_progress/models.py
nonebot_plugin_trans_progress/scheduler.py
nonebot_plugin_trans_progress/templates/index.html
nonebot_plugin_trans_progress/utils.py
nonebot_plugin_trans_progress/web.py
nonebot_plugin_trans_progress-0.3.8.dist-info/WHEEL
nonebot_plugin_trans_progress-0.3.8.dist-info/METADATA
nonebot_plugin_trans_progress-0.3.8.dist-info/RECORD
