Metadata-Version: 2.3
Name: nonebot-plugin-trans-progress
Version: 0.3.8
Summary: 记录和管理漫画汉化组的工作进度
Author: padoru233
Requires-Dist: httpx>=0.27.0,<1.0.0
Requires-Dist: nonebot-plugin-alconna>=0.60.0,<1.0.0
Requires-Dist: nonebot-plugin-apscheduler>=0.5.0,<1.0.0
Requires-Dist: nonebot-plugin-localstore>=0.7.4,<1.0.0
Requires-Dist: nonebot2>=2.4.3,<3.0.0
Requires-Dist: nonebot2[fastapi]>=2.4.2,<3.0.0
Requires-Dist: nonebot-adapter-onebot>=2.0.0,<3.0.0
Requires-Dist: tortoise-orm[asyncpg]>=0.21.0
Requires-Dist: pytz>=2024.2
Requires-Python: >=3.10
Project-URL: Homepage, https://github.com/padoru233/nonebot-plugin-trans-progress
Project-URL: Issues, https://github.com/padoru233/nonebot-plugin-trans-progress/issues
Project-URL: Repository, https://github.com/padoru233/nonebot-plugin-trans-progress.git
